kac/__init__.py
kac/changelog/__init__.py
kac/changelog/changelog.py
kac/changelog/release.py
kac/changelog/util.py
kac/kac.py
kac/templates/CHANGELOG.md
kac/util.py
kac-0.5.0.dist-info/entry_points.txt
kac-0.5.0.dist-info/LICENSE
kac-0.5.0.dist-info/WHEEL
kac-0.5.0.dist-info/METADATA
kac-0.5.0.dist-info/RECORD
